{
  "project_info": {
    "project_number": "163671621768",
    "firebase_url": "https://platepal-manz-default-rtdb.europe-west1.firebasedatabase.app",
    "project_id": "platepal-manz",
    "storage_bucket": "platepal-manz.appspot.com"
  },
  "client": [
    {
      "client_info": {
        "mobilesdk_app_id": "1:163671621768:android:371b6fd958f86044825f3d",
        "android_client_info": {
          "package_name": "com.platepal.android"
        }
      },
      "oauth_client": [
        {
          "client_id": "163671621768-0tltuu9jsaidslidrhldqhbmehcgqd2r.apps.googleusercontent.com",
          "client_type": 3
        }
      ],
      "api_key": [
        {
          "current_key": "AIzaSyDnCN6AXZT55dpmG4fym1YafHTpEnvTXbs"
        }
      ],
      "services": {
        "appinvite_service": {
          "other_platform_oauth_client": [
            {
              "client_id": "163671621768-0tltuu9jsaidslidrhldqhbmehcgqd2r.apps.googleusercontent.com",
              "client_type": 3
            },
            {
              "client_id": "163671621768-0s1hfsik6gm1gr5j3b0di8p0801gjh36.apps.googleusercontent.com",
              "client_type": 2,
              "ios_info": {
                "bundle_id": "com.platePal.ios",
                "app_store_id": "6450932254"
              }
            }
          ]
        }
      }
    },
    {
      "client_info": {
        "mobilesdk_app_id": "1:163671621768:android:0f8f5bc88b0a6bbc825f3d",
        "android_client_info": {
          "package_name": "com.platepal.android"
        }
      },
      "oauth_client": [
        {
          "client_id": "163671621768-0tltuu9jsaidslidrhldqhbmehcgqd2r.apps.googleusercontent.com",
          "client_type": 3
        }
      ],
      "api_key": [
        {
          "current_key": "AIzaSyDnCN6AXZT55dpmG4fym1YafHTpEnvTXbs"
        }
      ],
      "services": {
        "appinvite_service": {
          "other_platform_oauth_client": [
            {
              "client_id": "163671621768-0tltuu9jsaidslidrhldqhbmehcgqd2r.apps.googleusercontent.com",
              "client_type": 3
            },
            {
              "client_id": "163671621768-0s1hfsik6gm1gr5j3b0di8p0801gjh36.apps.googleusercontent.com",
              "client_type": 2,
              "ios_info": {
                "bundle_id": "com.platePal.ios",
                "app_store_id": "6450932254"
              }
            }
          ]
        }
      }
    }
  ],
  "configuration_version": "1"
}